funcflow/__init__.py
funcflow/core.py
funcflow/messages.py
funcflow/prompt.py
funcflow/serialize.py
funcflow/utils.py
funcflow-0.0.3.dist-info/METADATA
funcflow-0.0.3.dist-info/WHEEL
funcflow-0.0.3.dist-info/RECORD
